[{"devId":"zhongqiaoyong@hikvision.com","nCommits":1,"nCommittedPyFiles":2,"nRepoTotalCommits":94,"nIntroductions":0,"nRemovals":2,"IEntropy":0.0,"REntropy":1.0,"nFilesInIntroductions":0,"nFilesInRemovals":2},{"devId":"xmyqsh@gmail.com","nCommits":1,"nCommittedPyFiles":1,"nRepoTotalCommits":94,"nIntroductions":0,"nRemovals":0,"IEntropy":0.0,"REntropy":0.0,"nFilesInIntroductions":0,"nFilesInRemovals":0},{"devId":"madhavbansal.cse18@itbhu.ac.in","nCommits":1,"nCommittedPyFiles":1,"nRepoTotalCommits":94,"nIntroductions":1,"nRemovals":0,"IEntropy":0.0,"REntropy":0.0,"nFilesInIntroductions":1,"nFilesInRemovals":0},{"devId":"ruhansa.123@gmail.com","nCommits":1,"nCommittedPyFiles":2,"nRepoTotalCommits":94,"nIntroductions":2,"nRemovals":0,"IEntropy":1.0,"REntropy":0.0,"nFilesInIntroductions":2,"nFilesInRemovals":0},{"devId":"platero.yang@gmail.com","nCommits":84,"nCommittedPyFiles":30,"nRepoTotalCommits":94,"nIntroductions":68,"nRemovals":38,"IEntropy":0.9254287597415755,"REntropy":0.9277894591909509,"nFilesInIntroductions":29,"nFilesInRemovals":18},{"devId":"tete1030@gmail.com","nCommits":2,"nCommittedPyFiles":2,"nRepoTotalCommits":94,"nIntroductions":0,"nRemovals":0,"IEntropy":0.0,"REntropy":0.0,"nFilesInIntroductions":0,"nFilesInRemovals":0},{"devId":"weigq1234@gmail.com","nCommits":1,"nCommittedPyFiles":1,"nRepoTotalCommits":94,"nIntroductions":1,"nRemovals":0,"IEntropy":0.0,"REntropy":0.0,"nFilesInIntroductions":1,"nFilesInRemovals":0},{"devId":"prnvb15@gmail.com","nCommits":3,"nCommittedPyFiles":1,"nRepoTotalCommits":94,"nIntroductions":1,"nRemovals":1,"IEntropy":0.0,"REntropy":0.0,"nFilesInIntroductions":1,"nFilesInRemovals":1}]