[{"devId":"42869932+annikabrundyn@users.noreply.github.com","mapCSCategoryIn":{"Warning":29,"Convention":33,"Error":33,"Refactor":17,"Fatal":0},"mapCSCategoryRm":{"Warning":3,"Convention":2,"Error":0,"Refactor":1,"Fatal":0}},{"devId":"briankosw@gmail.com","mapCSCategoryIn":{"Warning":3,"Convention":14,"Error":4,"Refactor":8,"Fatal":0},"mapCSCategoryRm":{"Warning":0,"Convention":2,"Error":1,"Refactor":0,"Fatal":0}},{"devId":"waf2107@columbia.edu","mapCSCategoryIn":{"Warning":190,"Convention":240,"Error":154,"Refactor":94,"Fatal":1},"mapCSCategoryRm":{"Warning":71,"Convention":79,"Error":52,"Refactor":26,"Fatal":0}},{"devId":"gokcen.eraslan@gmail.com","mapCSCategoryIn":{"Warning":1,"Convention":1,"Error":0,"Refactor":0,"Fatal":0},"mapCSCategoryRm":{"Warning":0,"Convention":0,"Error":0,"Refactor":0,"Fatal":0}},{"devId":"defiler.off@gmail.com","mapCSCategoryIn":{"Warning":0,"Convention":0,"Error":0,"Refactor":0,"Fatal":0},"mapCSCategoryRm":{"Warning":0,"Convention":0,"Error":0,"Refactor":0,"Fatal":0}},{"devId":"JackMLangerman@gmail.com","mapCSCategoryIn":{"Warning":0,"Convention":0,"Error":0,"Refactor":0,"Fatal":0},"mapCSCategoryRm":{"Warning":0,"Convention":0,"Error":0,"Refactor":0,"Fatal":0}},{"devId":"43908213+praecipue@users.noreply.github.com","mapCSCategoryIn":{"Warning":0,"Convention":0,"Error":0,"Refactor":0,"Fatal":0},"mapCSCategoryRm":{"Warning":0,"Convention":0,"Error":0,"Refactor":0,"Fatal":0}},{"devId":"ganprad@users.noreply.github.com","mapCSCategoryIn":{"Warning":0,"Convention":0,"Error":0,"Refactor":1,"Fatal":0},"mapCSCategoryRm":{"Warning":0,"Convention":0,"Error":0,"Refactor":0,"Fatal":0}},{"devId":"nodet.pierre@gmail.com","mapCSCategoryIn":{"Warning":0,"Convention":0,"Error":0,"Refactor":0,"Fatal":0},"mapCSCategoryRm":{"Warning":0,"Convention":0,"Error":0,"Refactor":0,"Fatal":0}},{"devId":"blahblahj.wsy@gmail.com","mapCSCategoryIn":{"Warning":6,"Convention":11,"Error":12,"Refactor":6,"Fatal":0},"mapCSCategoryRm":{"Warning":0,"Convention":0,"Error":0,"Refactor":0,"Fatal":0}},{"devId":"haswanth.kumar.39@gmail.com","mapCSCategoryIn":{"Warning":2,"Convention":3,"Error":4,"Refactor":1,"Fatal":0},"mapCSCategoryRm":{"Warning":2,"Convention":1,"Error":0,"Refactor":2,"Fatal":0}},{"devId":"66853113+pre-commit-ci[bot]@users.noreply.github.com","mapCSCategoryIn":{"Warning":0,"Convention":0,"Error":0,"Refactor":0,"Fatal":0},"mapCSCategoryRm":{"Warning":0,"Convention":0,"Error":0,"Refactor":0,"Fatal":0}},{"devId":"47659865+maximzubkov@users.noreply.github.com","mapCSCategoryIn":{"Warning":0,"Convention":1,"Error":0,"Refactor":0,"Fatal":0},"mapCSCategoryRm":{"Warning":0,"Convention":0,"Error":0,"Refactor":0,"Fatal":0}},{"devId":"daniel.youngho.kim@gmail.com","mapCSCategoryIn":{"Warning":0,"Convention":0,"Error":0,"Refactor":0,"Fatal":0},"mapCSCategoryRm":{"Warning":0,"Convention":0,"Error":0,"Refactor":0,"Fatal":0}},{"devId":"NiWaRe@users.noreply.github.com","mapCSCategoryIn":{"Warning":0,"Convention":0,"Error":0,"Refactor":0,"Fatal":0},"mapCSCategoryRm":{"Warning":0,"Convention":0,"Error":0,"Refactor":0,"Fatal":0}},{"devId":"nxr9266@g.rit.edu","mapCSCategoryIn":{"Warning":16,"Convention":12,"Error":10,"Refactor":7,"Fatal":0},"mapCSCategoryRm":{"Warning":6,"Convention":17,"Error":5,"Refactor":1,"Fatal":0}},{"devId":"ewah1g13@soton.ac.uk","mapCSCategoryIn":{"Warning":0,"Convention":0,"Error":0,"Refactor":0,"Fatal":0},"mapCSCategoryRm":{"Warning":0,"Convention":0,"Error":0,"Refactor":0,"Fatal":0}},{"devId":"abhayrawat2695@gmail.com","mapCSCategoryIn":{"Warning":0,"Convention":2,"Error":1,"Refactor":0,"Fatal":0},"mapCSCategoryRm":{"Warning":0,"Convention":0,"Error":0,"Refactor":0,"Fatal":0}},{"devId":"jirka.borovec@seznam.cz","mapCSCategoryIn":{"Warning":4,"Convention":33,"Error":17,"Refactor":3,"Fatal":1},"mapCSCategoryRm":{"Warning":18,"Convention":52,"Error":27,"Refactor":18,"Fatal":0}},{"devId":"Kessido@Gmail.com","mapCSCategoryIn":{"Warning":0,"Convention":0,"Error":0,"Refactor":0,"Fatal":0},"mapCSCategoryRm":{"Warning":0,"Convention":1,"Error":0,"Refactor":1,"Fatal":0}},{"devId":"fabrice.normandin@gmail.com","mapCSCategoryIn":{"Warning":0,"Convention":0,"Error":0,"Refactor":0,"Fatal":0},"mapCSCategoryRm":{"Warning":0,"Convention":0,"Error":0,"Refactor":0,"Fatal":0}},{"devId":"nitta@akihironitta.com","mapCSCategoryIn":{"Warning":5,"Convention":78,"Error":59,"Refactor":3,"Fatal":0},"mapCSCategoryRm":{"Warning":42,"Convention":39,"Error":12,"Refactor":0,"Fatal":0}},{"devId":"richard@richard-stanton.com","mapCSCategoryIn":{"Warning":0,"Convention":0,"Error":0,"Refactor":0,"Fatal":0},"mapCSCategoryRm":{"Warning":0,"Convention":0,"Error":0,"Refactor":0,"Fatal":0}},{"devId":"57919375+FlorianMF@users.noreply.github.com","mapCSCategoryIn":{"Warning":0,"Convention":0,"Error":0,"Refactor":0,"Fatal":0},"mapCSCategoryRm":{"Warning":0,"Convention":0,"Error":0,"Refactor":0,"Fatal":0}},{"devId":"sean@grid.ai","mapCSCategoryIn":{"Warning":5,"Convention":9,"Error":12,"Refactor":6,"Fatal":0},"mapCSCategoryRm":{"Warning":3,"Convention":6,"Error":2,"Refactor":0,"Fatal":0}},{"devId":"michael@dudalev.com","mapCSCategoryIn":{"Warning":0,"Convention":1,"Error":0,"Refactor":0,"Fatal":0},"mapCSCategoryRm":{"Warning":0,"Convention":0,"Error":0,"Refactor":0,"Fatal":0}},{"devId":"teddy.koker@gmail.com","mapCSCategoryIn":{"Warning":13,"Convention":9,"Error":13,"Refactor":6,"Fatal":0},"mapCSCategoryRm":{"Warning":0,"Convention":4,"Error":1,"Refactor":3,"Fatal":0}},{"devId":"jeremy.adams.fisher@gmail.com","mapCSCategoryIn":{"Warning":0,"Convention":0,"Error":0,"Refactor":0,"Fatal":0},"mapCSCategoryRm":{"Warning":0,"Convention":0,"Error":0,"Refactor":0,"Fatal":0}},{"devId":"jirka@pytorchlightning.ai","mapCSCategoryIn":{"Warning":0,"Convention":0,"Error":0,"Refactor":0,"Fatal":0},"mapCSCategoryRm":{"Warning":0,"Convention":2,"Error":0,"Refactor":0,"Fatal":0}},{"devId":"def6488@gmail.com","mapCSCategoryIn":{"Warning":0,"Convention":0,"Error":0,"Refactor":0,"Fatal":0},"mapCSCategoryRm":{"Warning":0,"Convention":0,"Error":0,"Refactor":0,"Fatal":0}},{"devId":"47032123+sorenrasmussenai@users.noreply.github.com","mapCSCategoryIn":{"Warning":0,"Convention":0,"Error":1,"Refactor":0,"Fatal":0},"mapCSCategoryRm":{"Warning":0,"Convention":1,"Error":0,"Refactor":0,"Fatal":0}},{"devId":"ydcjeff@outlook.com","mapCSCategoryIn":{"Warning":1,"Convention":3,"Error":5,"Refactor":0,"Fatal":0},"mapCSCategoryRm":{"Warning":0,"Convention":1,"Error":0,"Refactor":0,"Fatal":0}},{"devId":"25852061+zhengyu-yang@users.noreply.github.com","mapCSCategoryIn":{"Warning":3,"Convention":1,"Error":1,"Refactor":1,"Fatal":0},"mapCSCategoryRm":{"Warning":1,"Convention":2,"Error":1,"Refactor":2,"Fatal":0}},{"devId":"sidhant96@outlook.com","mapCSCategoryIn":{"Warning":1,"Convention":3,"Error":3,"Refactor":2,"Fatal":0},"mapCSCategoryRm":{"Warning":0,"Convention":0,"Error":0,"Refactor":0,"Fatal":0}},{"devId":"zehua.cheng@cs.ox.ac.uk","mapCSCategoryIn":{"Warning":0,"Convention":0,"Error":0,"Refactor":0,"Fatal":0},"mapCSCategoryRm":{"Warning":0,"Convention":0,"Error":0,"Refactor":0,"Fatal":0}},{"devId":"poiret.clement@outlook.fr","mapCSCategoryIn":{"Warning":0,"Convention":2,"Error":0,"Refactor":0,"Fatal":0},"mapCSCategoryRm":{"Warning":0,"Convention":0,"Error":0,"Refactor":0,"Fatal":0}},{"devId":"35857753+thiyagu145@users.noreply.github.com","mapCSCategoryIn":{"Warning":0,"Convention":0,"Error":0,"Refactor":0,"Fatal":0},"mapCSCategoryRm":{"Warning":0,"Convention":0,"Error":0,"Refactor":0,"Fatal":0}},{"devId":"donaljbyrne@me.com","mapCSCategoryIn":{"Warning":29,"Convention":35,"Error":43,"Refactor":31,"Fatal":1},"mapCSCategoryRm":{"Warning":12,"Convention":19,"Error":14,"Refactor":10,"Fatal":0}},{"devId":"tv.github@beamnet.de","mapCSCategoryIn":{"Warning":0,"Convention":0,"Error":0,"Refactor":0,"Fatal":0},"mapCSCategoryRm":{"Warning":0,"Convention":0,"Error":0,"Refactor":0,"Fatal":0}},{"devId":"Sepehr.Sameni@gmail.com","mapCSCategoryIn":{"Warning":0,"Convention":0,"Error":0,"Refactor":0,"Fatal":0},"mapCSCategoryRm":{"Warning":0,"Convention":0,"Error":0,"Refactor":0,"Fatal":0}},{"devId":"julian.w.francis@gmail.com","mapCSCategoryIn":{"Warning":0,"Convention":0,"Error":0,"Refactor":0,"Fatal":0},"mapCSCategoryRm":{"Warning":0,"Convention":0,"Error":0,"Refactor":0,"Fatal":0}},{"devId":"hector_laria@hotmail.com","mapCSCategoryIn":{"Warning":0,"Convention":3,"Error":0,"Refactor":2,"Fatal":0},"mapCSCategoryRm":{"Warning":1,"Convention":6,"Error":0,"Refactor":1,"Fatal":0}},{"devId":"32468150+BartekRoszak@users.noreply.github.com","mapCSCategoryIn":{"Warning":0,"Convention":0,"Error":0,"Refactor":0,"Fatal":0},"mapCSCategoryRm":{"Warning":0,"Convention":0,"Error":0,"Refactor":0,"Fatal":0}},{"devId":"justindujardin@users.noreply.github.com","mapCSCategoryIn":{"Warning":0,"Convention":0,"Error":0,"Refactor":0,"Fatal":0},"mapCSCategoryRm":{"Warning":0,"Convention":0,"Error":0,"Refactor":0,"Fatal":0}},{"devId":"theaniketmaurya@gmail.com","mapCSCategoryIn":{"Warning":0,"Convention":0,"Error":0,"Refactor":0,"Fatal":0},"mapCSCategoryRm":{"Warning":0,"Convention":0,"Error":0,"Refactor":0,"Fatal":0}},{"devId":"95carolineelizabeth@gmail.com","mapCSCategoryIn":{"Warning":0,"Convention":0,"Error":0,"Refactor":0,"Fatal":0},"mapCSCategoryRm":{"Warning":0,"Convention":0,"Error":0,"Refactor":0,"Fatal":0}},{"devId":"aedu.waelchli@gmail.com","mapCSCategoryIn":{"Warning":6,"Convention":7,"Error":9,"Refactor":6,"Fatal":0},"mapCSCategoryRm":{"Warning":0,"Convention":0,"Error":0,"Refactor":0,"Fatal":0}},{"devId":"sean.narenthiran@gmail.com","mapCSCategoryIn":{"Warning":0,"Convention":0,"Error":0,"Refactor":0,"Fatal":0},"mapCSCategoryRm":{"Warning":0,"Convention":0,"Error":0,"Refactor":0,"Fatal":0}},{"devId":"40417707+deng-cy@users.noreply.github.com","mapCSCategoryIn":{"Warning":0,"Convention":1,"Error":0,"Refactor":0,"Fatal":0},"mapCSCategoryRm":{"Warning":0,"Convention":0,"Error":0,"Refactor":2,"Fatal":0}},{"devId":"sugatoray@users.noreply.github.com","mapCSCategoryIn":{"Warning":2,"Convention":5,"Error":5,"Refactor":3,"Fatal":0},"mapCSCategoryRm":{"Warning":0,"Convention":0,"Error":0,"Refactor":0,"Fatal":0}},{"devId":"HenryJia@users.noreply.github.com","mapCSCategoryIn":{"Warning":3,"Convention":2,"Error":3,"Refactor":1,"Fatal":0},"mapCSCategoryRm":{"Warning":0,"Convention":0,"Error":0,"Refactor":0,"Fatal":0}},{"devId":"marijansmetko123@gmail.com","mapCSCategoryIn":{"Warning":1,"Convention":3,"Error":1,"Refactor":1,"Fatal":0},"mapCSCategoryRm":{"Warning":0,"Convention":0,"Error":0,"Refactor":0,"Fatal":0}},{"devId":"danielshats1@gmail.com","mapCSCategoryIn":{"Warning":0,"Convention":0,"Error":0,"Refactor":0,"Fatal":0},"mapCSCategoryRm":{"Warning":0,"Convention":0,"Error":0,"Refactor":0,"Fatal":0}},{"devId":"ananya@pytorchlightning.ai","mapCSCategoryIn":{"Warning":27,"Convention":35,"Error":28,"Refactor":22,"Fatal":0},"mapCSCategoryRm":{"Warning":20,"Convention":20,"Error":9,"Refactor":10,"Fatal":0}},{"devId":"45285388+kaushikb11@users.noreply.github.com","mapCSCategoryIn":{"Warning":1,"Convention":1,"Error":0,"Refactor":0,"Fatal":0},"mapCSCategoryRm":{"Warning":0,"Convention":0,"Error":0,"Refactor":0,"Fatal":0}},{"devId":"777Jonathansum@gmail.com","mapCSCategoryIn":{"Warning":0,"Convention":0,"Error":0,"Refactor":0,"Fatal":0},"mapCSCategoryRm":{"Warning":0,"Convention":0,"Error":0,"Refactor":0,"Fatal":0}},{"devId":"35718590+hoangtnm@users.noreply.github.com","mapCSCategoryIn":{"Warning":0,"Convention":0,"Error":0,"Refactor":0,"Fatal":0},"mapCSCategoryRm":{"Warning":0,"Convention":0,"Error":0,"Refactor":0,"Fatal":0}},{"devId":"bartol.k@gmail.com","mapCSCategoryIn":{"Warning":0,"Convention":0,"Error":0,"Refactor":0,"Fatal":0},"mapCSCategoryRm":{"Warning":0,"Convention":0,"Error":0,"Refactor":0,"Fatal":0}},{"devId":"PawelKobojek@gmail.com","mapCSCategoryIn":{"Warning":2,"Convention":2,"Error":1,"Refactor":1,"Fatal":0},"mapCSCategoryRm":{"Warning":0,"Convention":1,"Error":0,"Refactor":0,"Fatal":0}},{"devId":"79456372+Programmer-RD-AI@users.noreply.github.com","mapCSCategoryIn":{"Warning":1,"Convention":0,"Error":0,"Refactor":0,"Fatal":0},"mapCSCategoryRm":{"Warning":0,"Convention":0,"Error":0,"Refactor":0,"Fatal":0}},{"devId":"36888863+brambozz@users.noreply.github.com","mapCSCategoryIn":{"Warning":0,"Convention":0,"Error":0,"Refactor":0,"Fatal":0},"mapCSCategoryRm":{"Warning":0,"Convention":0,"Error":0,"Refactor":0,"Fatal":0}},{"devId":"wonjaekim@kakao.com","mapCSCategoryIn":{"Warning":1,"Convention":2,"Error":0,"Refactor":1,"Fatal":0},"mapCSCategoryRm":{"Warning":0,"Convention":0,"Error":0,"Refactor":0,"Fatal":0}},{"devId":"36116534+chris-clem@users.noreply.github.com","mapCSCategoryIn":{"Warning":7,"Convention":24,"Error":24,"Refactor":13,"Fatal":0},"mapCSCategoryRm":{"Warning":0,"Convention":5,"Error":4,"Refactor":4,"Fatal":0}},{"devId":"34589654+mxksowie@users.noreply.github.com","mapCSCategoryIn":{"Warning":0,"Convention":0,"Error":0,"Refactor":0,"Fatal":0},"mapCSCategoryRm":{"Warning":0,"Convention":0,"Error":1,"Refactor":0,"Fatal":0}},{"devId":"76759666+layne-sadler@users.noreply.github.com","mapCSCategoryIn":{"Warning":0,"Convention":0,"Error":0,"Refactor":0,"Fatal":0},"mapCSCategoryRm":{"Warning":0,"Convention":0,"Error":0,"Refactor":0,"Fatal":0}},{"devId":"aniketmaurya@outlook.com","mapCSCategoryIn":{"Warning":1,"Convention":1,"Error":2,"Refactor":0,"Fatal":1},"mapCSCategoryRm":{"Warning":0,"Convention":0,"Error":0,"Refactor":0,"Fatal":0}},{"devId":"makadiyajyot2121@gmail.com","mapCSCategoryIn":{"Warning":1,"Convention":0,"Error":1,"Refactor":0,"Fatal":0},"mapCSCategoryRm":{"Warning":0,"Convention":1,"Error":0,"Refactor":0,"Fatal":0}},{"devId":"carlossmocholi@gmail.com","mapCSCategoryIn":{"Warning":0,"Convention":0,"Error":0,"Refactor":0,"Fatal":0},"mapCSCategoryRm":{"Warning":0,"Convention":0,"Error":0,"Refactor":0,"Fatal":0}},{"devId":"seppo.git@marjaniemi.com","mapCSCategoryIn":{"Warning":4,"Convention":5,"Error":5,"Refactor":4,"Fatal":0},"mapCSCategoryRm":{"Warning":0,"Convention":0,"Error":0,"Refactor":0,"Fatal":0}},{"devId":"47158509+oke-aditya@users.noreply.github.com","mapCSCategoryIn":{"Warning":6,"Convention":14,"Error":12,"Refactor":5,"Fatal":0},"mapCSCategoryRm":{"Warning":0,"Convention":1,"Error":0,"Refactor":0,"Fatal":0}},{"devId":"56754322+garryod@users.noreply.github.com","mapCSCategoryIn":{"Warning":0,"Convention":2,"Error":0,"Refactor":0,"Fatal":0},"mapCSCategoryRm":{"Warning":0,"Convention":0,"Error":0,"Refactor":0,"Fatal":0}},{"devId":"vincentwarmerdam@gmail.com","mapCSCategoryIn":{"Warning":0,"Convention":0,"Error":0,"Refactor":0,"Fatal":0},"mapCSCategoryRm":{"Warning":0,"Convention":0,"Error":0,"Refactor":0,"Fatal":0}},{"devId":"mangustalex11@gmail.com","mapCSCategoryIn":{"Warning":1,"Convention":0,"Error":1,"Refactor":1,"Fatal":0},"mapCSCategoryRm":{"Warning":0,"Convention":0,"Error":0,"Refactor":0,"Fatal":0}},{"devId":"46056525+shashank2000@users.noreply.github.com","mapCSCategoryIn":{"Warning":0,"Convention":0,"Error":0,"Refactor":0,"Fatal":0},"mapCSCategoryRm":{"Warning":0,"Convention":0,"Error":0,"Refactor":0,"Fatal":0}},{"devId":"frederic.branchaud-charron@elementai.com","mapCSCategoryIn":{"Warning":0,"Convention":0,"Error":0,"Refactor":0,"Fatal":0},"mapCSCategoryRm":{"Warning":1,"Convention":1,"Error":1,"Refactor":0,"Fatal":0}},{"devId":"20610905+akihironitta@users.noreply.github.com","mapCSCategoryIn":{"Warning":0,"Convention":0,"Error":0,"Refactor":0,"Fatal":0},"mapCSCategoryRm":{"Warning":0,"Convention":0,"Error":0,"Refactor":0,"Fatal":0}},{"devId":"walterj.nelson@mail.utoronto.ca","mapCSCategoryIn":{"Warning":1,"Convention":0,"Error":0,"Refactor":0,"Fatal":0},"mapCSCategoryRm":{"Warning":0,"Convention":0,"Error":0,"Refactor":0,"Fatal":0}},{"devId":"souravraha@users.noreply.github.com","mapCSCategoryIn":{"Warning":0,"Convention":0,"Error":0,"Refactor":0,"Fatal":0},"mapCSCategoryRm":{"Warning":1,"Convention":0,"Error":0,"Refactor":1,"Fatal":0}},{"devId":"62050782+deepsource-autofix[bot]@users.noreply.github.com","mapCSCategoryIn":{"Warning":0,"Convention":0,"Error":0,"Refactor":0,"Fatal":0},"mapCSCategoryRm":{"Warning":5,"Convention":10,"Error":5,"Refactor":7,"Fatal":0}},{"devId":"66261195+edenlightning@users.noreply.github.com","mapCSCategoryIn":{"Warning":0,"Convention":0,"Error":0,"Refactor":0,"Fatal":0},"mapCSCategoryRm":{"Warning":0,"Convention":0,"Error":0,"Refactor":0,"Fatal":0}},{"devId":"indigoviolet@users.noreply.github.com","mapCSCategoryIn":{"Warning":0,"Convention":2,"Error":1,"Refactor":2,"Fatal":0},"mapCSCategoryRm":{"Warning":0,"Convention":0,"Error":0,"Refactor":0,"Fatal":0}},{"devId":"tridao@users.noreply.github.com","mapCSCategoryIn":{"Warning":0,"Convention":0,"Error":0,"Refactor":0,"Fatal":0},"mapCSCategoryRm":{"Warning":0,"Convention":0,"Error":0,"Refactor":0,"Fatal":0}},{"devId":"Borda@users.noreply.github.com","mapCSCategoryIn":{"Warning":103,"Convention":199,"Error":134,"Refactor":51,"Fatal":0},"mapCSCategoryRm":{"Warning":80,"Convention":113,"Error":43,"Refactor":35,"Fatal":0}},{"devId":"NathanJMichlo@gmail.com","mapCSCategoryIn":{"Warning":1,"Convention":0,"Error":0,"Refactor":0,"Fatal":0},"mapCSCategoryRm":{"Warning":0,"Convention":0,"Error":0,"Refactor":0,"Fatal":0}},{"devId":"43241560+zlapp@users.noreply.github.com","mapCSCategoryIn":{"Warning":2,"Convention":5,"Error":5,"Refactor":3,"Fatal":0},"mapCSCategoryRm":{"Warning":0,"Convention":0,"Error":0,"Refactor":0,"Fatal":0}},{"devId":"44038824+arvindmuralie77@users.noreply.github.com","mapCSCategoryIn":{"Warning":0,"Convention":0,"Error":0,"Refactor":0,"Fatal":0},"mapCSCategoryRm":{"Warning":0,"Convention":0,"Error":0,"Refactor":0,"Fatal":0}},{"devId":"39116809+norabelrose@users.noreply.github.com","mapCSCategoryIn":{"Warning":0,"Convention":1,"Error":0,"Refactor":0,"Fatal":0},"mapCSCategoryRm":{"Warning":0,"Convention":0,"Error":0,"Refactor":0,"Fatal":0}},{"devId":"rohitgr1998@gmail.com","mapCSCategoryIn":{"Warning":0,"Convention":0,"Error":0,"Refactor":0,"Fatal":0},"mapCSCategoryRm":{"Warning":0,"Convention":0,"Error":0,"Refactor":0,"Fatal":0}},{"devId":"ryancentralorg@gmail.com","mapCSCategoryIn":{"Warning":0,"Convention":0,"Error":0,"Refactor":0,"Fatal":0},"mapCSCategoryRm":{"Warning":0,"Convention":0,"Error":0,"Refactor":0,"Fatal":0}},{"devId":"kou.yongkang@dhs.sg","mapCSCategoryIn":{"Warning":0,"Convention":0,"Error":0,"Refactor":0,"Fatal":0},"mapCSCategoryRm":{"Warning":0,"Convention":0,"Error":0,"Refactor":0,"Fatal":0}},{"devId":"miccio-dk@users.noreply.github.com","mapCSCategoryIn":{"Warning":0,"Convention":1,"Error":0,"Refactor":0,"Fatal":0},"mapCSCategoryRm":{"Warning":1,"Convention":0,"Error":0,"Refactor":0,"Fatal":0}},{"devId":"abhishek16005@iiitd.ac.in","mapCSCategoryIn":{"Warning":0,"Convention":0,"Error":0,"Refactor":0,"Fatal":0},"mapCSCategoryRm":{"Warning":0,"Convention":0,"Error":0,"Refactor":0,"Fatal":0}}]