[{"id":"4e446307c1ee8b7369321e0bbb9cc95aa1d8e20d","author":"canma.love@gmail.com","date":"Nov 25, 2018, 3:22:22 PM","listPyFileLintMsg":[{"path":"bert/__init__.py","mapLintMsgCount":{}},{"path":"bert/create_pretraining_data.py","mapLintMsgCount":{"R1702":2,"C0103":8,"R1714":1,"R0205":1,"R0914":4,"R0915":1,"R0912":1,"R0913":3,"E0401":2,"C0209":7,"C0206":1,"C0116":3,"W0311":229}},{"path":"bert/extract_features.py","mapLintMsgCount":{"C0103":3,"R0205":2,"R0903":2,"R0914":2,"R0913":1,"E0401":3,"C0209":8,"W0311":177,"C0115":1,"C0116":1}},{"path":"bert/modeling.py","mapLintMsgCount":{"F0010":1}},{"path":"bert/modeling_test.py","mapLintMsgCount":{"R1702":1,"C0114":1,"C0103":13,"R0205":1,"R0914":2,"R0912":1,"R0902":1,"R0913":1,"E0401":3,"C0209":1,"C0206":1,"C0115":2,"C0116":5,"W0311":154}},{"path":"bert/optimization.py","mapLintMsgCount":{"R1725":1,"C0103":4,"R0914":1,"R0903":1,"R0913":1,"E0401":1,"W0311":66,"W0613":1,"R0201":1}},{"path":"bert/optimization_test.py","mapLintMsgCount":{"C0114":1,"C0103":2,"R0903":1,"E0401":2,"W0311":17,"C0115":1,"C0116":1}},{"path":"bert/run_classifier.py","mapLintMsgCount":{"C0103":12,"R0205":3,"R0903":2,"R0914":4,"R0915":1,"R0913":2,"E0401":4,"C0209":18,"R0201":3,"C0116":1,"W0311":422,"W0223":1,"R1719":2}},{"path":"bert/run_pretraining.py","mapLintMsgCount":{"C0103":10,"R0914":1,"R0915":2,"R0913":3,"E0401":3,"C0209":4,"W0311":166,"C0116":1}},{"path":"bert/run_squad.py","mapLintMsgCount":{"R1702":1,"C0103":18,"R0205":3,"C0200":1,"R0903":1,"R0914":7,"R0915":3,"R0912":4,"R0913":6,"R0902":1,"E0401":5,"C0209":28,"C0302":1,"R1730":1,"C0116":2,"W0311":613}},{"path":"bert/tokenization.py","mapLintMsgCount":{"C0103":4,"R1714":2,"R0205":3,"R0903":2,"R1705":4,"R1716":12,"E0401":2,"C0209":4,"E0602":2,"C0116":5,"R0201":4,"W0311":210,"R0916":2}},{"path":"bert/tokenization_test.py","mapLintMsgCount":{"C0114":1,"W1406":27,"E0401":2,"W0311":57,"W0212":18,"C0115":1,"C0116":9}},{"path":"bert_lstm_ner.py","mapLintMsgCount":{"F0010":1}},{"path":"tf_metrics.py","mapLintMsgCount":{"C0103":22,"R0914":1,"R0913":4,"R1705":1,"E0401":3,"C0304":1,"W0621":3,"R1721":1,"R1710":1,"C0303":1,"C0116":1}}]},{"id":"cfc952ed53e4e37fc19f2c2aba4df48f55990c4b","parentCommit":"5ece2a1c4d007fa7dbad9f0bde358c2e04235454","author":"canma.love@gmail.com","date":"Nov 25, 2018, 5:34:58 PM","listPyFileLintMsg":[]},{"id":"8639ee977133d8bd9cf5a6426bdf458496bf5ee2","parentCommit":"cfc952ed53e4e37fc19f2c2aba4df48f55990c4b","author":"canma.love@gmail.com","date":"Nov 25, 2018, 9:59:38 PM","listPyFileLintMsg":[{"path":"bert_lstm_ner.py","mapLintMsgCount":{"F0010":1}},{"path":"lstm_crf_layer.py","mapLintMsgCount":{"F0010":1}}]},{"id":"2d6e015147b426764e84dad25ecbca4c25930ba0","parentCommit":"8639ee977133d8bd9cf5a6426bdf458496bf5ee2","author":"canma.love@gmail.com","date":"Nov 25, 2018, 10:12:01 PM","listPyFileLintMsg":[]},{"id":"bd30f9c0cb4f87738aedc1a0893fd0b368c21a49","parentCommit":"2d6e015147b426764e84dad25ecbca4c25930ba0","author":"canma.love@gmail.com","date":"Nov 25, 2018, 10:13:04 PM","listPyFileLintMsg":[]},{"id":"50f9793447625968ee225f37aa878c56473f180d","parentCommit":"bd30f9c0cb4f87738aedc1a0893fd0b368c21a49","author":"canma.love@gmail.com","date":"Nov 25, 2018, 11:11:56 PM","listPyFileLintMsg":[{"path":"bert_lstm_ner.py","mapLintMsgCount":{"F0010":1}}]},{"id":"385722587e44a29cb1cdc6bdcac5088122cc1fbb","parentCommit":"50f9793447625968ee225f37aa878c56473f180d","author":"canma.love@gmail.com","date":"Nov 26, 2018, 11:52:56 AM","listPyFileLintMsg":[{"path":"bert_lstm_ner.py","mapLintMsgCount":{"F0010":1}},{"path":"lstm_crf_layer.py","mapLintMsgCount":{"F0010":1}}]},{"id":"1d107b3127ce155ec2a1d28e317b99717592fe7f","parentCommit":"385722587e44a29cb1cdc6bdcac5088122cc1fbb","author":"canma.love@gmail.com","date":"Nov 26, 2018, 12:04:57 PM","listPyFileLintMsg":[{"path":"bert_lstm_ner.py","mapLintMsgCount":{"F0010":1}}]},{"id":"3864a9d4a54bb631830a608d7cba8d05cf759bd5","parentCommit":"1d107b3127ce155ec2a1d28e317b99717592fe7f","author":"canma.love@gmail.com","date":"Nov 27, 2018, 3:20:14 PM","listPyFileLintMsg":[]},{"id":"5373a8b075f3d3c19e440d7ffaf121c234ea1cf3","parentCommit":"3864a9d4a54bb631830a608d7cba8d05cf759bd5","author":"canma.love@gmail.com","date":"Nov 27, 2018, 6:55:08 PM","listPyFileLintMsg":[{"path":"bert_lstm_ner.py","mapLintMsgCount":{"F0010":1}},{"path":"conlleval.py","mapLintMsgCount":{"C0114":1,"C0103":16,"R0205":1,"C0321":20,"R0903":1,"R0914":1,"R0915":1,"R0912":1,"R0902":1,"C0209":22,"C0304":1,"C0415":1,"E1307":1,"C0115":2,"C0116":12,"W0311":2,"W1514":1}},{"path":"lstm_crf_layer.py","mapLintMsgCount":{"F0010":1}}]},{"id":"d5054b26aac0a51adbf6f41bb5b0042af28e6b52","parentCommit":"5373a8b075f3d3c19e440d7ffaf121c234ea1cf3","author":"canma.love@gmail.com","date":"Nov 27, 2018, 7:01:35 PM","listPyFileLintMsg":[{"path":"bert_lstm_ner.py","mapLintMsgCount":{"F0010":1}}]},{"id":"d523c6d58030bf505b5de1bdb73754042b5b5e0b","parentCommit":"d5054b26aac0a51adbf6f41bb5b0042af28e6b52","author":"ma_cancan@163.com","date":"Dec 7, 2018, 10:47:45 PM","listPyFileLintMsg":[{"path":"bert_lstm_ner.py","mapLintMsgCount":{"F0010":1}},{"path":"lstm_crf_layer.py","mapLintMsgCount":{"F0010":1}}]},{"id":"2be597cfc4441e3274560a7ae54b3e7489dfb4bd","parentCommit":"d523c6d58030bf505b5de1bdb73754042b5b5e0b","author":"ma_cancan@163.com","date":"Dec 12, 2018, 1:46:42 PM","listPyFileLintMsg":[]},{"id":"c35178d4c35957a351715c103a02fa3f3f883f60","parentCommit":"2be597cfc4441e3274560a7ae54b3e7489dfb4bd","author":"ma_cancan@163.com","date":"Dec 12, 2018, 1:47:20 PM","listPyFileLintMsg":[]},{"id":"78285a066d143f190f32d9fdf02392c4f30b457b","parentCommit":"c35178d4c35957a351715c103a02fa3f3f883f60","author":"macanv1@hotmail.com","date":"Dec 15, 2018, 2:59:41 PM","listPyFileLintMsg":[]},{"id":"f524f9de5b2c7361808c33ca7c598542525abe65","parentCommit":"78285a066d143f190f32d9fdf02392c4f30b457b","author":"macanv1@hotmail.com","date":"Dec 15, 2018, 3:04:12 PM","listPyFileLintMsg":[]},{"id":"cc2fb32f5af43382d6163591288a81f0c54a02ff","parentCommit":"f524f9de5b2c7361808c33ca7c598542525abe65","author":"macanv1@hotmail.com","date":"Dec 15, 2018, 3:21:16 PM","listPyFileLintMsg":[{"path":"bert_lstm_ner.py","mapLintMsgCount":{"F0010":1}}]},{"id":"4c7c7f7e530ee8f5b8d9b80b38ff4dbf8e4176fe","parentCommit":"cc2fb32f5af43382d6163591288a81f0c54a02ff","author":"macanv1@hotmail.com","date":"Dec 18, 2018, 11:30:52 AM","listPyFileLintMsg":[{"path":"bert_lstm_ner.py","mapLintMsgCount":{"F0010":1}}]},{"id":"a40f5d87372e48b11fc02b4735560b003ad8da2a","parentCommit":"4c7c7f7e530ee8f5b8d9b80b38ff4dbf8e4176fe","author":"canma.love@gmail.com","date":"Jan 3, 2019, 12:15:18 PM","listPyFileLintMsg":[{"path":"bert_lstm_ner.py","mapLintMsgCount":{"F0010":1}},{"path":"lstm_crf_layer.py","mapLintMsgCount":{"F0010":1}},{"path":"terminal_predict.py","mapLintMsgCount":{"F0010":1}}]},{"id":"2183006cad08eca611f9fd8070b72e37f9f056dd","parentCommit":"a40f5d87372e48b11fc02b4735560b003ad8da2a","author":"canma.love@gmail.com","date":"Jan 3, 2019, 1:01:58 PM","listPyFileLintMsg":[]},{"id":"7f6b9163d0c59bb85b8b0ad7ee537a8600d9bf93","parentCommit":"2183006cad08eca611f9fd8070b72e37f9f056dd","author":"canma.love@gmail.com","date":"Jan 3, 2019, 1:02:48 PM","listPyFileLintMsg":[]},{"id":"c1840c046e500b1bfba9811d42a751bb04a3e0c4","parentCommit":"a40f5d87372e48b11fc02b4735560b003ad8da2a","author":"canma.love@gmail.com","date":"Jan 3, 2019, 2:48:30 PM","listPyFileLintMsg":[{"path":"terminal_predict.py","mapLintMsgCount":{"F0010":1}}]},{"id":"cb1e676de9ce36073500271f5d592d5a08bec1b6","parentCommit":"c1840c046e500b1bfba9811d42a751bb04a3e0c4","author":"canma.love@gmail.com","date":"Jan 3, 2019, 2:48:51 PM","listPyFileLintMsg":[]},{"id":"cb1e676de9ce36073500271f5d592d5a08bec1b6","parentCommit":"7f6b9163d0c59bb85b8b0ad7ee537a8600d9bf93","author":"canma.love@gmail.com","date":"Jan 3, 2019, 2:48:51 PM","listPyFileLintMsg":[{"path":"terminal_predict.py","mapLintMsgCount":{"F0010":1}}]},{"id":"47504f875d03700ff1e887b41b223281ff52fb8f","parentCommit":"cb1e676de9ce36073500271f5d592d5a08bec1b6","author":"canma.love@gmail.com","date":"Jan 3, 2019, 2:52:20 PM","listPyFileLintMsg":[]},{"id":"8dba8889ac27a77145767074660d1b1044055000","parentCommit":"47504f875d03700ff1e887b41b223281ff52fb8f","author":"canma.love@gmail.com","date":"Jan 4, 2019, 4:39:54 PM","listPyFileLintMsg":[{"path":"bert_lstm_ner.py","mapLintMsgCount":{"F0010":1}}]},{"id":"8bc5b70cafc031cf9590c7535a3eb2b5f1163b97","parentCommit":"8dba8889ac27a77145767074660d1b1044055000","author":"canma.love@gmail.com","date":"Jan 9, 2019, 10:45:40 AM","listPyFileLintMsg":[{"path":"bert_lstm_ner.py","mapLintMsgCount":{"F0010":1}}]},{"id":"38be0881159711231322eef4df5f15eab675f97f","parentCommit":"8bc5b70cafc031cf9590c7535a3eb2b5f1163b97","author":"canma.love@gmail.com","date":"Jan 9, 2019, 3:51:00 PM","listPyFileLintMsg":[{"path":"bert_lstm_ner.py","mapLintMsgCount":{"F0010":1}},{"path":"data_process.py","mapLintMsgCount":{"F0010":1}},{"path":"terminal_predict.py","mapLintMsgCount":{"F0010":1}}]},{"id":"424f043a10d394440051310917fdf4f54d66767a","parentCommit":"38be0881159711231322eef4df5f15eab675f97f","author":"ma_cancan@163.com","date":"Jan 30, 2019, 6:57:09 PM","listPyFileLintMsg":[{"path":"bert/extract_features.py","mapLintMsgCount":{"F0010":1}},{"path":"bert/tokenization.py","mapLintMsgCount":{"C0103":4,"R1714":2,"R0205":3,"R0903":2,"R1705":4,"R1716":12,"E0401":2,"C0209":4,"E0602":2,"C0116":5,"R0201":4,"W0311":210,"R0916":2,"W0511":1}},{"path":"client/__init__.py","mapLintMsgCount":{"C0304":1}},{"path":"client/client.py","mapLintMsgCount":{"C0301":35,"C0103":13,"R0205":1,"C0123":1,"E1102":1,"W0707":3,"E1101":1,"R0902":1,"R0913":1,"R1705":2,"E0401":3,"C0209":15,"E0213":2,"C1802":2,"R1720":2,"R1710":2,"C0415":1,"C0115":2,"W0231":1,"W0221":4,"W0621":1,"W0613":1}},{"path":"client_test.py","mapLintMsgCount":{"F0010":1}},{"path":"run.py","mapLintMsgCount":{"F0010":1}},{"path":"runs/__init__.py","mapLintMsgCount":{"E0401":4,"C0304":1,"C0415":5,"C0116":3}},{"path":"server/__init__.py","mapLintMsgCount":{"C0304":1}},{"path":"server/graph.py","mapLintMsgCount":{"F0010":1}},{"path":"server/helper.py","mapLintMsgCount":{"F0010":1}},{"path":"server/http.py","mapLintMsgCount":{"C0301":1,"C0114":1,"C0103":2,"W0707":2,"E0401":1,"C0209":1,"E0402":1,"C0415":5,"C0115":1,"C0116":1}},{"path":"server/server.py","mapLintMsgCount":{"F0010":1}},{"path":"server/zmq_decor.py","mapLintMsgCount":{"C0301":1,"C0114":1,"R1725":1,"C0411":1,"R0903":1,"E0401":2,"W0201":1,"W0612":1,"C0116":1}},{"path":"setup.py","mapLintMsgCount":{"C0301":3,"C0114":1,"R1732":1,"W0611":2}},{"path":"terminal_predict.py","mapLintMsgCount":{"F0010":1}},{"path":"train/__init__.py","mapLintMsgCount":{"C0304":1}},{"path":"train/bert_lstm_ner.py","mapLintMsgCount":{"F0010":1}},{"path":"train/conlleval.py","mapLintMsgCount":{"C0114":1,"C0103":16,"R0205":1,"C0321":20,"R0903":1,"R0914":1,"R0915":1,"R0912":1,"R0902":1,"C0209":22,"C0304":1,"C0415":1,"E1307":1,"C0115":2,"C0116":12,"W0311":2,"W1514":1}},{"path":"train/lstm_crf_layer.py","mapLintMsgCount":{"F0010":1}},{"path":"train/models.py","mapLintMsgCount":{"F0010":1}},{"path":"train/tf_metrics.py","mapLintMsgCount":{"C0301":1,"C0103":22,"R0914":1,"R0913":4,"R1705":1,"E0401":3,"C0304":1,"W0621":3,"R1721":1,"R1710":1,"C0303":1,"C0116":1}},{"path":"train/train_helper.py","mapLintMsgCount":{"C0301":5,"E0402":1,"W1401":1,"C0415":1,"C0116":1}}]},{"id":"d326afffb901ee04a9314b3cb988808a205aba02","parentCommit":"424f043a10d394440051310917fdf4f54d66767a","author":"ma_cancan@163.com","date":"Jan 30, 2019, 6:58:17 PM","listPyFileLintMsg":[]},{"id":"1c98cabc81c30f418f7e12a934e733665751d7a6","parentCommit":"d326afffb901ee04a9314b3cb988808a205aba02","author":"ma_cancan@163.com","date":"Jan 30, 2019, 7:57:29 PM","listPyFileLintMsg":[]},{"id":"a21e804eee691ebb88784a16dc7b77a14122a23d","parentCommit":"1c98cabc81c30f418f7e12a934e733665751d7a6","author":"ma_cancan@163.com","date":"Jan 30, 2019, 10:09:29 PM","listPyFileLintMsg":[{"path":"bert_base/__init__.py","mapLintMsgCount":{"C0304":1}},{"path":"client_test.py","mapLintMsgCount":{"F0010":1}},{"path":"run.py","mapLintMsgCount":{"F0010":1}},{"path":"setup.py","mapLintMsgCount":{"C0301":3,"C0114":1,"R1732":1,"W0611":2}},{"path":"terminal_predict.py","mapLintMsgCount":{"F0010":1}}]},{"id":"bb28c225ca3d9f5fcc43eed1c92a3a6127469371","parentCommit":"a21e804eee691ebb88784a16dc7b77a14122a23d","author":"ma_cancan@163.com","date":"Jan 30, 2019, 10:14:13 PM","listPyFileLintMsg":[]},{"id":"3e9d476e29197a96c01bb743a8357d5e16063636","parentCommit":"bb28c225ca3d9f5fcc43eed1c92a3a6127469371","author":"ma_cancan@163.com","date":"Jan 30, 2019, 10:19:07 PM","listPyFileLintMsg":[]},{"id":"29aba425d2d2f5428437c372c3ef3db89adb644a","parentCommit":"bb28c225ca3d9f5fcc43eed1c92a3a6127469371","author":"ma_cancan@163.com","date":"Feb 11, 2019, 10:40:42 AM","listPyFileLintMsg":[{"path":"bert_base/bert/__init__.py","mapLintMsgCount":{}},{"path":"bert_base/bert/create_pretraining_data.py","mapLintMsgCount":{"R1702":2,"C0103":8,"R1714":1,"R0205":1,"R0914":4,"R0915":1,"R0912":1,"R0913":3,"E0401":2,"C0209":7,"C0206":1,"C0116":3,"W0311":229}},{"path":"bert_base/bert/extract_features.py","mapLintMsgCount":{"F0010":1}},{"path":"bert_base/bert/modeling.py","mapLintMsgCount":{"F0010":1}},{"path":"bert_base/bert/modeling_test.py","mapLintMsgCount":{"R1702":1,"C0114":1,"C0103":13,"R0205":1,"R0914":2,"R0912":1,"R0902":1,"R0913":1,"E0401":3,"C0209":1,"C0206":1,"C0115":2,"C0116":5,"W0311":154}},{"path":"bert_base/bert/optimization.py","mapLintMsgCount":{"R1725":1,"C0103":4,"R0914":1,"R0903":1,"R0913":1,"E0401":1,"W0311":66,"W0613":1,"R0201":1}},{"path":"bert_base/bert/optimization_test.py","mapLintMsgCount":{"C0114":1,"C0103":2,"R0903":1,"E0401":2,"W0311":17,"C0115":1,"C0116":1}},{"path":"bert_base/bert/run_classifier.py","mapLintMsgCount":{"C0103":12,"R0205":3,"R0903":2,"R0914":4,"R0915":1,"R0913":2,"E0401":4,"C0209":18,"R0201":3,"C0116":1,"W0311":422,"W0223":1,"R1719":2}},{"path":"bert_base/bert/run_pretraining.py","mapLintMsgCount":{"C0103":10,"R0914":1,"R0915":2,"R0913":3,"E0401":3,"C0209":4,"W0311":166,"C0116":1}},{"path":"bert_base/bert/run_squad.py","mapLintMsgCount":{"R1702":1,"C0103":18,"R0205":3,"C0200":1,"R0903":1,"R0914":7,"R0915":3,"R0912":4,"R0913":6,"R0902":1,"E0401":5,"C0209":28,"C0302":1,"R1730":1,"C0116":2,"W0311":613}},{"path":"bert_base/bert/tokenization.py","mapLintMsgCount":{"C0103":4,"R1714":2,"R0205":3,"R0903":2,"R1705":4,"R1716":12,"E0401":2,"C0209":4,"E0602":2,"C0116":5,"R0201":4,"W0311":210,"R0916":2,"W0511":1}},{"path":"bert_base/bert/tokenization_test.py","mapLintMsgCount":{"C0114":1,"W1406":27,"E0401":2,"W0311":57,"W0212":18,"C0115":1,"C0116":9}},{"path":"bert_base/client/__init__.py","mapLintMsgCount":{"C0301":35,"C0103":13,"R0205":1,"C0123":1,"E1102":1,"W0707":3,"E1101":1,"R0902":1,"R0913":1,"R1705":2,"E0401":3,"C0209":15,"E0213":2,"C1802":2,"R1720":2,"R1710":2,"C0415":1,"C0115":2,"W0231":1,"W0221":4,"W0621":1,"W0613":1}},{"path":"bert_base/runs/__init__.py","mapLintMsgCount":{"C0301":1,"E0401":4,"C0209":2,"W0125":1,"C0304":1,"C0415":6,"C0116":3}},{"path":"bert_base/server/__init__.py","mapLintMsgCount":{"F0010":1}},{"path":"bert_base/server/graph.py","mapLintMsgCount":{"F0010":1}},{"path":"bert_base/server/helper.py","mapLintMsgCount":{"F0010":1}},{"path":"bert_base/server/http.py","mapLintMsgCount":{"C0301":1,"C0114":1,"C0103":2,"W0707":2,"E0401":1,"C0209":1,"E0402":1,"C0415":5,"C0115":1,"C0116":1}},{"path":"bert_base/server/zmq_decor.py","mapLintMsgCount":{"C0301":1,"C0114":1,"R1725":1,"C0411":1,"R0903":1,"E0401":2,"W0201":1,"W0612":1,"C0116":1}},{"path":"bert_base/train/__init__.py","mapLintMsgCount":{"C0304":1}},{"path":"bert_base/train/bert_lstm_ner.py","mapLintMsgCount":{"F0010":1}},{"path":"bert_base/train/conlleval.py","mapLintMsgCount":{"C0114":1,"C0103":16,"R0205":1,"C0321":20,"R0903":1,"R0914":1,"R0915":1,"R0912":1,"R0902":1,"C0209":22,"C0304":1,"C0415":1,"E1307":1,"C0115":2,"C0116":12,"W0311":2,"W1514":1}},{"path":"bert_base/train/lstm_crf_layer.py","mapLintMsgCount":{"F0010":1}},{"path":"bert_base/train/models.py","mapLintMsgCount":{"F0010":1}},{"path":"bert_base/train/tf_metrics.py","mapLintMsgCount":{"C0301":1,"C0103":22,"R0914":1,"R0913":4,"R1705":1,"E0401":3,"C0304":1,"W0621":3,"R1721":1,"R1710":1,"C0303":1,"C0116":1}},{"path":"bert_base/train/train_helper.py","mapLintMsgCount":{"C0301":5,"E0402":1,"W1401":1,"C0415":1,"C0116":1}}]},{"id":"b2cef0be9572b01b2f1284093d38c0ba65bd0006","parentCommit":"29aba425d2d2f5428437c372c3ef3db89adb644a","author":"ma_cancan@163.com","date":"Feb 11, 2019, 10:41:15 AM","listPyFileLintMsg":[]},{"id":"b2cef0be9572b01b2f1284093d38c0ba65bd0006","parentCommit":"3e9d476e29197a96c01bb743a8357d5e16063636","author":"ma_cancan@163.com","date":"Feb 11, 2019, 10:41:15 AM","listPyFileLintMsg":[{"path":"bert_base/bert/__init__.py","mapLintMsgCount":{}},{"path":"bert_base/bert/create_pretraining_data.py","mapLintMsgCount":{"R1702":2,"C0103":8,"R1714":1,"R0205":1,"R0914":4,"R0915":1,"R0912":1,"R0913":3,"E0401":2,"C0209":7,"C0206":1,"C0116":3,"W0311":229}},{"path":"bert_base/bert/extract_features.py","mapLintMsgCount":{"F0010":1}},{"path":"bert_base/bert/modeling.py","mapLintMsgCount":{"F0010":1}},{"path":"bert_base/bert/modeling_test.py","mapLintMsgCount":{"R1702":1,"C0114":1,"C0103":13,"R0205":1,"R0914":2,"R0912":1,"R0902":1,"R0913":1,"E0401":3,"C0209":1,"C0206":1,"C0115":2,"C0116":5,"W0311":154}},{"path":"bert_base/bert/optimization.py","mapLintMsgCount":{"R1725":1,"C0103":4,"R0914":1,"R0903":1,"R0913":1,"E0401":1,"W0311":66,"W0613":1,"R0201":1}},{"path":"bert_base/bert/optimization_test.py","mapLintMsgCount":{"C0114":1,"C0103":2,"R0903":1,"E0401":2,"W0311":17,"C0115":1,"C0116":1}},{"path":"bert_base/bert/run_classifier.py","mapLintMsgCount":{"C0103":12,"R0205":3,"R0903":2,"R0914":4,"R0915":1,"R0913":2,"E0401":4,"C0209":18,"R0201":3,"C0116":1,"W0311":422,"W0223":1,"R1719":2}},{"path":"bert_base/bert/run_pretraining.py","mapLintMsgCount":{"C0103":10,"R0914":1,"R0915":2,"R0913":3,"E0401":3,"C0209":4,"W0311":166,"C0116":1}},{"path":"bert_base/bert/run_squad.py","mapLintMsgCount":{"R1702":1,"C0103":18,"R0205":3,"C0200":1,"R0903":1,"R0914":7,"R0915":3,"R0912":4,"R0913":6,"R0902":1,"E0401":5,"C0209":28,"C0302":1,"R1730":1,"C0116":2,"W0311":613}},{"path":"bert_base/bert/tokenization.py","mapLintMsgCount":{"C0103":4,"R1714":2,"R0205":3,"R0903":2,"R1705":4,"R1716":12,"E0401":2,"C0209":4,"E0602":2,"C0116":5,"R0201":4,"W0311":210,"R0916":2,"W0511":1}},{"path":"bert_base/bert/tokenization_test.py","mapLintMsgCount":{"C0114":1,"W1406":27,"E0401":2,"W0311":57,"W0212":18,"C0115":1,"C0116":9}},{"path":"bert_base/client/__init__.py","mapLintMsgCount":{"C0301":35,"C0103":13,"R0205":1,"C0123":1,"E1102":1,"W0707":3,"E1101":1,"R0902":1,"R0913":1,"R1705":2,"E0401":3,"C0209":15,"E0213":2,"C1802":2,"R1720":2,"R1710":2,"C0415":1,"C0115":2,"W0231":1,"W0221":4,"W0621":1,"W0613":1}},{"path":"bert_base/runs/__init__.py","mapLintMsgCount":{"C0301":1,"E0401":4,"C0209":2,"W0125":1,"C0304":1,"C0415":6,"C0116":3}},{"path":"bert_base/server/__init__.py","mapLintMsgCount":{"F0010":1}},{"path":"bert_base/server/graph.py","mapLintMsgCount":{"F0010":1}},{"path":"bert_base/server/helper.py","mapLintMsgCount":{"F0010":1}},{"path":"bert_base/server/http.py","mapLintMsgCount":{"C0301":1,"C0114":1,"C0103":2,"W0707":2,"E0401":1,"C0209":1,"E0402":1,"C0415":5,"C0115":1,"C0116":1}},{"path":"bert_base/server/zmq_decor.py","mapLintMsgCount":{"C0301":1,"C0114":1,"R1725":1,"C0411":1,"R0903":1,"E0401":2,"W0201":1,"W0612":1,"C0116":1}},{"path":"bert_base/train/__init__.py","mapLintMsgCount":{"C0304":1}},{"path":"bert_base/train/bert_lstm_ner.py","mapLintMsgCount":{"F0010":1}},{"path":"bert_base/train/conlleval.py","mapLintMsgCount":{"C0114":1,"C0103":16,"R0205":1,"C0321":20,"R0903":1,"R0914":1,"R0915":1,"R0912":1,"R0902":1,"C0209":22,"C0304":1,"C0415":1,"E1307":1,"C0115":2,"C0116":12,"W0311":2,"W1514":1}},{"path":"bert_base/train/lstm_crf_layer.py","mapLintMsgCount":{"F0010":1}},{"path":"bert_base/train/models.py","mapLintMsgCount":{"F0010":1}},{"path":"bert_base/train/tf_metrics.py","mapLintMsgCount":{"C0301":1,"C0103":22,"R0914":1,"R0913":4,"R1705":1,"E0401":3,"C0304":1,"W0621":3,"R1721":1,"R1710":1,"C0303":1,"C0116":1}},{"path":"bert_base/train/train_helper.py","mapLintMsgCount":{"C0301":5,"E0402":1,"W1401":1,"C0415":1,"C0116":1}}]},{"id":"1a005ed78fe23dbc311781a05cb30d33bbf34b97","parentCommit":"b2cef0be9572b01b2f1284093d38c0ba65bd0006","author":"ma_cancan@163.com","date":"Feb 11, 2019, 12:20:20 PM","listPyFileLintMsg":[{"path":"bert_base/runs/__init__.py","mapLintMsgCount":{"C0301":1,"E0401":4,"C0209":2,"W0125":1,"C0304":1,"C0415":6,"C0116":3}},{"path":"bert_base/train/bert_lstm_ner.py","mapLintMsgCount":{"F0010":1}},{"path":"bert_base/train/train_helper.py","mapLintMsgCount":{"F0010":1}}]},{"id":"a3ae5f83a54856926892bff48d8de420f8f43a0f","parentCommit":"1a005ed78fe23dbc311781a05cb30d33bbf34b97","author":"ma_cancan@163.com","date":"Feb 11, 2019, 5:03:13 PM","listPyFileLintMsg":[{"path":"bert_base/server/graph.py","mapLintMsgCount":{"F0010":1}},{"path":"bert_base/train/bert_lstm_ner.py","mapLintMsgCount":{"F0010":1}},{"path":"bert_base/train/lstm_crf_layer.py","mapLintMsgCount":{"F0010":1}},{"path":"bert_base/train/models.py","mapLintMsgCount":{"F0010":1}}]},{"id":"ec1a40e62cc53655ac88588ecd1b419555c9232d","parentCommit":"a3ae5f83a54856926892bff48d8de420f8f43a0f","author":"ma_cancan@163.com","date":"Feb 11, 2019, 5:41:13 PM","listPyFileLintMsg":[{"path":"bert_base/train/bert_lstm_ner.py","mapLintMsgCount":{"F0010":1}},{"path":"bert_base/train/lstm_crf_layer.py","mapLintMsgCount":{"F0010":1}},{"path":"terminal_predict.py","mapLintMsgCount":{"F0010":1}}]},{"id":"c1aa61d9c095e621dd10c6756a1ae651eb1d54f6","parentCommit":"ec1a40e62cc53655ac88588ecd1b419555c9232d","author":"ma_cancan@163.com","date":"Feb 11, 2019, 6:21:41 PM","listPyFileLintMsg":[{"path":"bert_base/server/graph.py","mapLintMsgCount":{"F0010":1}},{"path":"bert_base/train/bert_lstm_ner.py","mapLintMsgCount":{"F0010":1}},{"path":"bert_base/train/lstm_crf_layer.py","mapLintMsgCount":{"F0010":1}}]},{"id":"a286935c71c91d0b6f4d3f0ca3190fedaf20ccb5","parentCommit":"c1aa61d9c095e621dd10c6756a1ae651eb1d54f6","author":"ma_cancan@163.com","date":"Feb 11, 2019, 6:32:23 PM","listPyFileLintMsg":[{"path":"setup.py","mapLintMsgCount":{"C0301":3,"C0114":1,"R1732":1,"W0611":2}}]},{"id":"f221eb01bc48bbf9a83b8b66f6c1845156e42131","parentCommit":"a286935c71c91d0b6f4d3f0ca3190fedaf20ccb5","author":"ma_cancan@163.com","date":"Feb 11, 2019, 8:24:18 PM","listPyFileLintMsg":[{"path":"bert_base/server/__init__.py","mapLintMsgCount":{"F0010":1}},{"path":"bert_base/server/helper.py","mapLintMsgCount":{"F0010":1}},{"path":"bert_base/train/bert_lstm_ner.py","mapLintMsgCount":{"F0010":1}}]},{"id":"609e017bc2c5893ef823dde65c4ec3d70f4bd0ee","parentCommit":"f221eb01bc48bbf9a83b8b66f6c1845156e42131","author":"ma_cancan@163.com","date":"Feb 13, 2019, 11:14:08 AM","listPyFileLintMsg":[{"path":"setup.py","mapLintMsgCount":{"C0301":3,"C0114":1,"R1732":1,"W0611":2}}]},{"id":"e456fb2c994f208479713918e0f2203c0d62035e","parentCommit":"609e017bc2c5893ef823dde65c4ec3d70f4bd0ee","author":"ma_cancan@163.com","date":"Feb 19, 2019, 3:20:42 PM","listPyFileLintMsg":[{"path":"bert_base/bert/extract_features.py","mapLintMsgCount":{"F0010":1}},{"path":"bert_base/client/__init__.py","mapLintMsgCount":{"C0301":35,"C0103":13,"R0205":1,"C0123":1,"E1102":1,"W0707":3,"E1101":1,"R0902":1,"R0913":1,"R1705":2,"E0401":3,"C0209":15,"E0213":2,"C1802":2,"R1720":2,"R1710":2,"C0415":1,"C0115":2,"W0231":1,"W0221":4,"W0621":1,"W0613":1}},{"path":"bert_base/runs/__init__.py","mapLintMsgCount":{"C0301":1,"E0401":4,"C0209":2,"W0125":1,"C0304":1,"C0415":6,"C0116":3}},{"path":"bert_base/server/__init__.py","mapLintMsgCount":{"F0010":1}},{"path":"bert_base/server/graph.py","mapLintMsgCount":{"F0010":1}},{"path":"bert_base/server/helper.py","mapLintMsgCount":{"F0010":1}},{"path":"bert_base/server/http.py","mapLintMsgCount":{"C0301":1,"C0114":1,"C0103":2,"W0707":2,"E0401":1,"C0209":1,"E0402":1,"C0415":5,"C0115":1,"C0116":1}},{"path":"bert_base/train/models.py","mapLintMsgCount":{"F0010":1}},{"path":"setup.py","mapLintMsgCount":{"C0301":3,"C0114":1,"R1732":1,"W0611":2}}]},{"id":"ef2d3699a765a6d5b09e8548b8aae91e372bff4a","parentCommit":"e456fb2c994f208479713918e0f2203c0d62035e","author":"ma_cancan@163.com","date":"Feb 19, 2019, 3:23:17 PM","listPyFileLintMsg":[]},{"id":"ba954b1c5bc63f460f014f98960186d769a526e6","parentCommit":"ef2d3699a765a6d5b09e8548b8aae91e372bff4a","author":"ma_cancan@163.com","date":"Feb 20, 2019, 10:38:49 AM","listPyFileLintMsg":[]},{"id":"4b7a2433ed91db2b3cdc11b5e2aa15eae0138e76","parentCommit":"ba954b1c5bc63f460f014f98960186d769a526e6","author":"master@evernightfireworks.com","date":"Feb 20, 2019, 1:56:37 PM","listPyFileLintMsg":[{"path":"bert_base/server/__init__.py","mapLintMsgCount":{"F0010":1}}]},{"id":"205ff58dc33ce82ffe8163583c4b0849bae5f8a9","parentCommit":"ba954b1c5bc63f460f014f98960186d769a526e6","author":"macanv1@hotmail.com","date":"Feb 20, 2019, 2:29:19 PM","listPyFileLintMsg":[{"path":"bert_base/server/__init__.py","mapLintMsgCount":{"F0010":1}}]},{"id":"205ff58dc33ce82ffe8163583c4b0849bae5f8a9","parentCommit":"4b7a2433ed91db2b3cdc11b5e2aa15eae0138e76","author":"macanv1@hotmail.com","date":"Feb 20, 2019, 2:29:19 PM","listPyFileLintMsg":[]},{"id":"3537b69b6a98ec95f1bd2c920f74f14f89dbe070","parentCommit":"205ff58dc33ce82ffe8163583c4b0849bae5f8a9","author":"ma_cancan@163.com","date":"Feb 25, 2019, 11:21:56 AM","listPyFileLintMsg":[{"path":"bert_base/server/graph.py","mapLintMsgCount":{"F0010":1}},{"path":"client_test.py","mapLintMsgCount":{"F0010":1}},{"path":"setup.py","mapLintMsgCount":{"C0301":3,"C0114":1,"R1732":1,"W0611":2}}]},{"id":"1792003420bd46126a1e7dc23c8c0eb3ef2ee286","parentCommit":"3537b69b6a98ec95f1bd2c920f74f14f89dbe070","author":"ma_cancan@163.com","date":"Mar 1, 2019, 5:51:36 PM","listPyFileLintMsg":[{"path":"bert_base/server/__init__.py","mapLintMsgCount":{"F0010":1}}]},{"id":"9f820782649286ad16ff6bfe8e566542e90741ec","parentCommit":"1792003420bd46126a1e7dc23c8c0eb3ef2ee286","author":"ma_cancan@163.com","date":"Mar 4, 2019, 11:19:53 AM","listPyFileLintMsg":[{"path":"bert_base/bert/extract_features.py","mapLintMsgCount":{"F0010":1}},{"path":"bert_base/bert/tokenization.py","mapLintMsgCount":{"C0103":4,"R1714":2,"R0205":3,"R0903":2,"R1705":4,"R1716":12,"E0401":2,"C0209":4,"C0305":1,"E0602":2,"C0116":5,"R0201":4,"W0311":210,"R0916":2,"W0511":1}},{"path":"client_test.py","mapLintMsgCount":{"F0010":1}},{"path":"setup.py","mapLintMsgCount":{"C0301":3,"C0114":1,"R1732":1,"W0611":2}}]},{"id":"ff9f88a79eccbbe5f20022eb6d4407c923983a27","parentCommit":"9f820782649286ad16ff6bfe8e566542e90741ec","author":"ma_cancan@163.com","date":"Mar 4, 2019, 5:49:07 PM","listPyFileLintMsg":[]},{"id":"f70592b82bebc06dbed259a9dca2870e486669f5","parentCommit":"9f820782649286ad16ff6bfe8e566542e90741ec","author":"ma_cancan@163.com","date":"Mar 6, 2019, 12:57:33 PM","listPyFileLintMsg":[{"path":"bert_base/train/train_helper.py","mapLintMsgCount":{"F0010":1}},{"path":"setup.py","mapLintMsgCount":{"C0301":3,"C0114":1,"R1732":1,"W0611":2}}]},{"id":"8509e8e65cc3ab03d911dba1aa45768e75701cae","parentCommit":"f70592b82bebc06dbed259a9dca2870e486669f5","author":"ma_cancan@163.com","date":"Mar 6, 2019, 2:02:31 PM","listPyFileLintMsg":[]},{"id":"8509e8e65cc3ab03d911dba1aa45768e75701cae","parentCommit":"ff9f88a79eccbbe5f20022eb6d4407c923983a27","author":"ma_cancan@163.com","date":"Mar 6, 2019, 2:02:31 PM","listPyFileLintMsg":[{"path":"bert_base/train/train_helper.py","mapLintMsgCount":{"F0010":1}},{"path":"setup.py","mapLintMsgCount":{"C0301":3,"C0114":1,"R1732":1,"W0611":2}}]},{"id":"67693d42d4f60d02fec9fb090ffcd7678bc7c0e7","parentCommit":"8509e8e65cc3ab03d911dba1aa45768e75701cae","author":"ma_cancan@163.com","date":"Mar 11, 2019, 12:34:33 PM","listPyFileLintMsg":[]},{"id":"f1a882fe50bae1fc3f0eecddb8108a773d1f7625","parentCommit":"67693d42d4f60d02fec9fb090ffcd7678bc7c0e7","author":"ma_cancan@163.com","date":"Apr 4, 2019, 12:42:56 PM","listPyFileLintMsg":[]},{"id":"dffe8ca247379c70762def4e1a9121a680b3f3a9","parentCommit":"f1a882fe50bae1fc3f0eecddb8108a773d1f7625","author":"ma_cancan@163.com","date":"Apr 4, 2019, 12:43:36 PM","listPyFileLintMsg":[]},{"id":"d5b1b739bce4b065c81281299849c17849dad165","parentCommit":"8509e8e65cc3ab03d911dba1aa45768e75701cae","author":"ma_cancan@163.com","date":"May 31, 2019, 11:06:56 AM","listPyFileLintMsg":[{"path":"bert_base/train/bert_lstm_ner.py","mapLintMsgCount":{"F0010":1}},{"path":"bert_base/train/train_helper.py","mapLintMsgCount":{"F0010":1}},{"path":"terminal_predict.py","mapLintMsgCount":{"F0010":1}}]},{"id":"fed90798883c8d6f631d586314b03eba50179081","parentCommit":"d5b1b739bce4b065c81281299849c17849dad165","author":"ma_cancan@163.com","date":"May 31, 2019, 11:07:17 AM","listPyFileLintMsg":[]},{"id":"fed90798883c8d6f631d586314b03eba50179081","parentCommit":"dffe8ca247379c70762def4e1a9121a680b3f3a9","author":"ma_cancan@163.com","date":"May 31, 2019, 11:07:17 AM","listPyFileLintMsg":[{"path":"bert_base/train/bert_lstm_ner.py","mapLintMsgCount":{"F0010":1}},{"path":"bert_base/train/train_helper.py","mapLintMsgCount":{"F0010":1}},{"path":"terminal_predict.py","mapLintMsgCount":{"F0010":1}}]},{"id":"86adbe420534d3d4c658c30e3714a67f6eacc83c","parentCommit":"fed90798883c8d6f631d586314b03eba50179081","author":"ma_cancan@163.com","date":"May 31, 2019, 11:13:20 AM","listPyFileLintMsg":[{"path":"run.py","mapLintMsgCount":{"F0010":1}}]},{"id":"9c9e7b1326a4189d70d807da831b14d02f2dafcb","parentCommit":"86adbe420534d3d4c658c30e3714a67f6eacc83c","author":"ma_cancan@163.com","date":"Jun 17, 2019, 11:03:16 AM","listPyFileLintMsg":[]},{"id":"32fd3c9ed695f9db103398fd5a5d54f04dfaa01a","parentCommit":"9c9e7b1326a4189d70d807da831b14d02f2dafcb","author":"327361201@qq.com","date":"Jul 12, 2019, 4:10:56 PM","listPyFileLintMsg":[{"path":"bert_base/server/graph.py","mapLintMsgCount":{"F0010":1}},{"path":"bert_base/server/helper.py","mapLintMsgCount":{"F0010":1}}]},{"id":"348c2ed87e279337d34fe1c2e35df1bcc9186287","parentCommit":"9c9e7b1326a4189d70d807da831b14d02f2dafcb","author":"ma_cancan@163.com","date":"Jul 24, 2019, 10:14:39 PM","listPyFileLintMsg":[{"path":"bert_base/server/graph.py","mapLintMsgCount":{"F0010":1}},{"path":"bert_base/server/helper.py","mapLintMsgCount":{"F0010":1}}]},{"id":"348c2ed87e279337d34fe1c2e35df1bcc9186287","parentCommit":"32fd3c9ed695f9db103398fd5a5d54f04dfaa01a","author":"ma_cancan@163.com","date":"Jul 24, 2019, 10:14:39 PM","listPyFileLintMsg":[]},{"id":"8e7f391314a6384fe015f5539f9ff57bd1bf8a83","parentCommit":"348c2ed87e279337d34fe1c2e35df1bcc9186287","author":"32366240@qq.com","date":"Sep 18, 2019, 9:57:29 AM","listPyFileLintMsg":[]},{"id":"37d36a2c2f3d9c6ff4e14224525cbe85dd4a448b","parentCommit":"348c2ed87e279337d34fe1c2e35df1bcc9186287","author":"canma.love@gmail.com","date":"Sep 21, 2019, 12:30:35 AM","listPyFileLintMsg":[{"path":"thu_classification.py","mapLintMsgCount":{"F0010":1}}]},{"id":"12fb822bd847f24e4de1beca8af9de34d1a794d2","parentCommit":"37d36a2c2f3d9c6ff4e14224525cbe85dd4a448b","author":"ma_cancan@163.com","date":"Sep 21, 2019, 10:06:06 AM","listPyFileLintMsg":[]},{"id":"12fb822bd847f24e4de1beca8af9de34d1a794d2","parentCommit":"8e7f391314a6384fe015f5539f9ff57bd1bf8a83","author":"ma_cancan@163.com","date":"Sep 21, 2019, 10:06:06 AM","listPyFileLintMsg":[{"path":"thu_classification.py","mapLintMsgCount":{"F0010":1}}]},{"id":"8fa51e8aaae8af69fa76bfd55eb52f959cffad68","parentCommit":"12fb822bd847f24e4de1beca8af9de34d1a794d2","author":"junting.guo0927@gmail.com","date":"Nov 7, 2019, 7:36:32 PM","listPyFileLintMsg":[{"path":"bert_base/server/__init__.py","mapLintMsgCount":{"F0010":1}},{"path":"bert_base/server/graph.py","mapLintMsgCount":{"F0010":1}}]},{"id":"ed3a547084723dc3d2a739c117d62d3b7bda6d7d","parentCommit":"12fb822bd847f24e4de1beca8af9de34d1a794d2","author":"ma_cancan@163.com","date":"Nov 11, 2019, 11:12:32 AM","listPyFileLintMsg":[{"path":"bert_base/server/__init__.py","mapLintMsgCount":{"F0010":1}},{"path":"bert_base/server/graph.py","mapLintMsgCount":{"F0010":1}}]},{"id":"ed3a547084723dc3d2a739c117d62d3b7bda6d7d","parentCommit":"8fa51e8aaae8af69fa76bfd55eb52f959cffad68","author":"ma_cancan@163.com","date":"Nov 11, 2019, 11:12:32 AM","listPyFileLintMsg":[]},{"id":"8892d3c0e0cbf51493b16079355109e0d6a7306b","parentCommit":"ed3a547084723dc3d2a739c117d62d3b7bda6d7d","author":"ma_cancan@163.com","date":"Nov 18, 2019, 10:54:37 AM","listPyFileLintMsg":[{"path":"bert_base/train/lstm_crf_layer.py","mapLintMsgCount":{"F0010":1}}]},{"id":"ccf3f093f0ac803e435cb8e8598fdddc2ba1105d","parentCommit":"8892d3c0e0cbf51493b16079355109e0d6a7306b","author":"ma_cancan@163.com","date":"Feb 6, 2020, 11:47:57 PM","listPyFileLintMsg":[{"path":"bert_base/server/helper.py","mapLintMsgCount":{"F0010":1}},{"path":"bert_base/server/simple_flask_http_service.py","mapLintMsgCount":{"F0010":1}}]}]